tiferet_flask/__init__.py
tiferet_flask/contexts/__init__.py
tiferet_flask/contexts/flask.py
tiferet_flask/contexts/request.py
tiferet_flask/contracts/__init__.py
tiferet_flask/contracts/flask.py
tiferet_flask/data/__init__.py
tiferet_flask/data/flask.py
tiferet_flask/handlers/__init__.py
tiferet_flask/handlers/flask.py
tiferet_flask/models/__init__.py
tiferet_flask/models/flask.py
tiferet_flask/proxies/__init__.py
tiferet_flask/proxies/yaml/__init__.py
tiferet_flask/proxies/yaml/flask.py
tiferet_flask-0.1.3.dist-info/licenses/LICENSE
tiferet_flask-0.1.3.dist-info/METADATA
tiferet_flask-0.1.3.dist-info/WHEEL
tiferet_flask-0.1.3.dist-info/top_level.txt
tiferet_flask-0.1.3.dist-info/RECORD
