Metadata-Version: 2.4
Name: tiferet-flask
Version: 0.1.3
Summary: An extension of the Tiferet Framework for the Flask API.
Author-email: "Andrew Shatz, Great Strength Systems" <andrew@greatstrength.me>
License: MIT
Project-URL: Homepage, https://github.com/greatstrength/tiferet-flask
Project-URL: Repository, https://github.com/greatstrength/tiferet-flask
Project-URL: Download, https://github.com/greatstrength/tiferet-flask
Requires-Python: >=3.10
License-File: LICENSE
Requires-Dist: tiferet>=1.7.0
Requires-Dist: flask>=3.1.2
Requires-Dist: flask_cors>=6.0.1
Provides-Extra: test
Requires-Dist: pytest>=8.3.3; extra == "test"
Requires-Dist: pytest_env>=1.1.5; extra == "test"
Dynamic: license-file
